Metadata-Version: 1.1
Name: client-corleone
Version: 0.1.6
Summary: A python experimental client for Telegram bot API you can't refuse
Home-page: https://github.com/sieira/client_corleone
Author: Luis Sieira
Author-email: luis.sieira@spacebar.fr
License: BSD
Platform: UNKNOWN
Classifier: Development Status :: 3 - Alpha
Classifier: Intended Audience :: Developers
Classifier: Topic :: Software Development :: Build Tools
Classifier: License :: OSI Approved :: BSD License
Classifier: Programming Language :: Python :: 3.6
Classifier: Programming Language :: Python :: 3.7
Classifier: Programming Language :: Python :: 3.8
